npspy/__init__.py
npspy/core.py
npspy-0.1.0.dist-info/LICENSE
npspy-0.1.0.dist-info/WHEEL
npspy-0.1.0.dist-info/METADATA
npspy-0.1.0.dist-info/RECORD
