Metadata-Version: 2.1
Name: npspy
Version: 0.1.0
Summary: 
Author: dr666m1
Author-email: skndr666m1@gmail.com
Requires-Python: >=3.9,<4.0
Classifier: Programming Language :: Python :: 3
Classifier: Programming Language :: Python :: 3.9
